{
  "resource": "Posts",
  "http_method": "GET",
  "route": "/v1/posts",
  "description": "Listing posts",
  "explanation": null,
  "parameters": [
    {
      "name": "page",
      "description": "Page"
    },
    {
      "name": "per_page",
      "description": "Items per page"
    }
  ],
  "response_fields": [

  ],
  "requests": [
    {
      "request_method": "GET",
      "request_path": "/v1/posts?page=1&per_page=25",
      "request_body": null,
      "request_headers": {
      },
      "request_query_parameters": {
        "page": "1",
        "per_page": "25"
      },
      "request_content_type": null,
      "response_status": 200,
      "response_status_text": "OK",
      "response_body": "{\"posts\":[{\"id\":1,\"title\":\"Ut asperiores et deleniti mollitia.\",\"text\":\"Et repudiandae sunt. Officia omnis fugiat quia iusto quidem exercitationem dolorem. Unde quod quibusdam omnis accusantium ex amet.\",\"comments\":[]},{\"id\":2,\"title\":\"Maiores tenetur cum laudantium sunt dolorem.\",\"text\":\"Qui qui quod. Rerum earum quae. Aliquid dolorem molestiae harum.\",\"comments\":[]}],\"meta\":{\"pagination\":{\"total\":2,\"per_page\":25,\"page\":1}}}",
      "response_headers": {
        "Content-Type": "application/json; charset=utf-8"
      },
      "response_content_type": "application/json; charset=utf-8",
      "curl": "curl \"http://localhost:5000/v1/posts?page=1&per_page=25\" -X GET "
    }
  ]
}